MANIFEST.in
README.rst
setup.py
myslx/__init__.py
myslx/blueprints.py
myslx/config.py
myslx/decorators.py
myslx/utils.py
myslx/templates/base.html
myslx/templates/logged_out.html
myslx_flask.egg-info/PKG-INFO
myslx_flask.egg-info/SOURCES.txt
myslx_flask.egg-info/dependency_links.txt
myslx_flask.egg-info/requires.txt
myslx_flask.egg-info/top_level.txt