Metadata-Version: 1.1
Name: myslx-flask
Version: 0.6.0
Summary: Integration components for mySolarlux for Flask based apps.
Home-page: https://git.solarlux.com/sl-it-dev/slx8174_myslx-flask/
Author: Enno Lohmeier
Author-email: e.lohmeier@solarlux.de
License: BSD License
Keywords: django auth account oauth
Platform: UNKNOWN
Classifier: Environment :: Web Environment
Classifier: Framework :: Flask
Classifier: Intended Audience :: Developers
Classifier: License :: OSI Approved :: BSD License
Classifier: Operating System :: OS Independent
Classifier: Programming Language :: Python
Classifier: Programming Language :: Python :: 3
Classifier: Programming Language :: Python :: 3.6
Classifier: Topic :: Internet :: WWW/HTTP
Classifier: Topic :: Internet :: WWW/HTTP :: Dynamic Content
